MANIFEST.in
setup.py
fish_bundles_web/__init__.py
fish_bundles_web/alembic.ini
fish_bundles_web/app.py
fish_bundles_web/bundles.py
fish_bundles_web/decorators.py
fish_bundles_web/docs.mkd
fish_bundles_web/git.py
fish_bundles_web/handlers.py
fish_bundles_web/login.py
fish_bundles_web/models.py
fish_bundles_web/version.py
fish_bundles_web.egg-info/PKG-INFO
fish_bundles_web.egg-info/SOURCES.txt
fish_bundles_web.egg-info/dependency_links.txt
fish_bundles_web.egg-info/entry_points.txt
fish_bundles_web.egg-info/requires.txt
fish_bundles_web.egg-info/top_level.txt
fish_bundles_web/config/__init__.py
fish_bundles_web/config/local.conf
fish_bundles_web/migrations/env.py
fish_bundles_web/migrations/versions/11a32e6c9a2a_remove_repo_and_org_from_bundle.py
fish_bundles_web/migrations/versions/16a56f702449_create_tags_table.py
fish_bundles_web/migrations/versions/17ba0e3cd9a3_create_organizations_table.py
fish_bundles_web/migrations/versions/22377ea227db_create_bundle_and_bundle_files_tables.py
fish_bundles_web/migrations/versions/263d18612078_add_configuration_to_repos.py
fish_bundles_web/migrations/versions/2886754ae3e9_create_repository_table.py
fish_bundles_web/migrations/versions/47a2ad7df96a_create_user_table.py
fish_bundles_web/migrations/versions/49989f23adc6_proper_unique_in_organizations.py
fish_bundles_web/migrations/versions/521232efdc0b_add_install_count_column.py
fish_bundles_web/migrations/versions/560af4d735a7_proper_unique_in_repo.py
fish_bundles_web/static/fonts/bootstrap/glyphicons-halflings-regular.eot
fish_bundles_web/static/fonts/bootstrap/glyphicons-halflings-regular.ttf
fish_bundles_web/static/fonts/bootstrap/glyphicons-halflings-regular.woff
fish_bundles_web/static/images/common-s2cf488c354.png
fish_bundles_web/static/images/sort_asc.png
fish_bundles_web/static/images/sort_both.png
fish_bundles_web/static/images/sort_desc.png
fish_bundles_web/static/images/common/check.png
fish_bundles_web/static/images/common/fish-logo.png
fish_bundles_web/static/images/common/fork.png
fish_bundles_web/static/images/common/github-light.png
fish_bundles_web/static/images/common/github.png
fish_bundles_web/static/images/common/logo.png
fish_bundles_web/static/images/common/small-logo.png
