Metadata-Version: 1.1
Name: fish-bundles-web
Version: 0.1.8
Summary: fish-bundles-web is the website for fish-bundles
Home-page: https://github.com/fish-bundles/fish-bundles-web
Author: Bernardo Heynemann
Author-email: heynemann@gmail.com
License: MIT
Keywords: fish shell repository share
Platform: UNKNOWN
Classifier: Development Status :: 4 - Beta
Classifier: Intended Audience :: Developers
Classifier: License :: OSI Approved :: MIT License
Classifier: Natural Language :: English
Classifier: Operating System :: Unix
Classifier: Programming Language :: Python :: 2.7
Classifier: Operating System :: OS Independent
